README.rst
setup.py
CAI/CAI.py
CAI/__init__.py
CAI/cli.py
CAI.egg-info/PKG-INFO
CAI.egg-info/PKG-INFO 2
CAI.egg-info/SOURCES.txt
CAI.egg-info/dependency_links.txt
CAI.egg-info/entry_points.txt
CAI.egg-info/requires.txt
CAI.egg-info/top_level.txt