Metadata-Version: 1.2
Name: CAI
Version: 1.0.3
Summary: Python implementation of codon adaptation index
Home-page: https://github.com/Benjamin-Lee/CodonAdaptationIndex
Author: Benjamin Lee
Author-email: benjamin_lee@college.harvard.edu
License: MIT
Platform: UNKNOWN
Classifier: Intended Audience :: Science/Research
Classifier: Topic :: Scientific/Engineering :: Bio-Informatics
Classifier: Programming Language :: Python
Requires-Python: >=3.4
